faviconer/__init__.py
faviconer/main.py
faviconer-0.1.5.dist-info/DESCRIPTION.rst
faviconer-0.1.5.dist-info/METADATA
faviconer-0.1.5.dist-info/RECORD
faviconer-0.1.5.dist-info/WHEEL
faviconer-0.1.5.dist-info/metadata.json
faviconer-0.1.5.dist-info/top_level.txt
