Metadata-Version: 2.0
Name: faviconer
Version: 0.1.5
Summary: faviconer is easy for get favicon package
Home-page: https://github.com/kuniiskywalker/faviconer
Author: kuniiskywalker
Author-email: kuniiskywalker@gmail.com
License: Apache License, Version 2.0
Platform: UNKNOWN
Classifier: Development Status :: 1 - Planning
Classifier: Programming Language :: Python
Classifier: Intended Audience :: Developers
Classifier: Operating System :: POSIX
Classifier: Programming Language :: Python :: 2
Classifier: Programming Language :: Python :: 2.7
Classifier: Programming Language :: Python :: 3
Classifier: Programming Language :: Python :: 3.5
Classifier: Programming Language :: Python :: 3.6
Classifier: Programming Language :: Python :: 3.7
Requires-Dist: beautifulsoup4 (==4.6.0)
Requires-Dist: requests (==2.22.0)
